elife_bus_sdk/__init__.py
elife_bus_sdk/events.py
elife_bus_sdk/exceptions.py
elife_bus_sdk/publishers/__init__.py
elife_bus_sdk/publishers/event_publisher.py
elife_bus_sdk/publishers/sns_publisher.py
elife_bus_sdk/queues/__init__.py
elife_bus_sdk/queues/message_queue.py
elife_bus_sdk/queues/sqs_queue.py
elife_bus_sdk-0.0.7.dist-info/LICENSE
elife_bus_sdk-0.0.7.dist-info/METADATA
elife_bus_sdk-0.0.7.dist-info/WHEEL
elife_bus_sdk-0.0.7.dist-info/top_level.txt
elife_bus_sdk-0.0.7.dist-info/RECORD
